llmtracer/__init__.py
llmtracer/convenience.py
llmtracer/frame_info.py
llmtracer/handlers/__init__.py
llmtracer/handlers/json_writer.py
llmtracer/handlers/svg_writer.py
llmtracer/handlers/trace_viewer.py
llmtracer/module_filtering.py
llmtracer/object_converter.py
llmtracer/testing/collections/__init__.py
llmtracer/testing/collections/mutable_mapping.py
llmtracer/testing/collections/mutable_set.py
llmtracer/testing/collections/tests/test_mutable_mapping_tests.py
llmtracer/testing/collections/tests/test_mutable_set_tests.py
llmtracer/tests/__init__.py
llmtracer/tests/integration_test_wandb.py
llmtracer/tests/test_object_converter.py
llmtracer/tests/test_trace_builder.py
llmtracer/tools/__init__.py
llmtracer/tools/trace_viewer/.gitignore
llmtracer/tools/trace_viewer/__init__.py
llmtracer/tools/trace_viewer/app/__init__.py
llmtracer/tools/trace_viewer/app/app.py
llmtracer/tools/trace_viewer/app/endpoint_integration.py
llmtracer/tools/trace_viewer/app/flame_graph.py
llmtracer/tools/trace_viewer/app/json_view.py
llmtracer/tools/trace_viewer/app/pcconfig.py
llmtracer/tools/trace_viewer/app_runner.py
llmtracer/tools/trace_viewer/assets/chakra_color_mode_provider.js
llmtracer/tools/trace_viewer/assets/favicon.ico
llmtracer/tools/trace_viewer/assets/react-json-view-lite.css
llmtracer/tools/trace_viewer/optimization_unit_trace_example.json
llmtracer/tools/trace_viewer/requirements.txt
llmtracer/tools/trace_viewer/rxconfig.py
llmtracer/trace_builder.py
llmtracer/trace_schema.py
llmtracer/utils/__init__.py
llmtracer/utils/callable_wrapper.py
llmtracer/utils/stopwatch_context.py
llmtracer/utils/tests/__init__.py
llmtracer/utils/tests/test_callable_wrapper.py
llmtracer/utils/tests/test_weakrefs.py
llmtracer/utils/weakrefs.py
llmtracer/wandb_integration.py
llmtracer-2.0.0.dist-info/LICENSE
llmtracer-2.0.0.dist-info/METADATA
llmtracer-2.0.0.dist-info/WHEEL
llmtracer-2.0.0.dist-info/entry_points.txt
llmtracer-2.0.0.dist-info/RECORD
