Metadata-Version: 2.1
Name: llmtracer
Version: 2.0.0
Summary: LLMTracer: A tool to trace the execution of a program that uses LLMs and visualize the results.
Home-page: https://github.com/blackhc/llmtracer
License: GPL-3.0-only
Author: Andreas Kirsch
Author-email: blackhc@gmail.com
Requires-Python: >=3.11,<4.0
Classifier: Development Status :: 4 - Beta
Classifier: Intended Audience :: Developers
Classifier: License :: OSI Approved :: GNU General Public License v3 (GPLv3)
Classifier: Natural Language :: English
Classifier: Programming Language :: Python :: 3
Classifier: Programming Language :: Python :: 3.11
Classifier: Programming Language :: Python :: 3.12
Provides-Extra: dev
Provides-Extra: test
Requires-Dist: black (>=22.12.0,<23.0.0) ; extra == "test"
Requires-Dist: bump2version (>=1.0.1,<2.0.0) ; extra == "dev"
Requires-Dist: flake8 (>=6.0.0,<7.0.0) ; extra == "test"
Requires-Dist: flake8-docstrings (>=1.6.0,<2.0.0) ; extra == "test"
Requires-Dist: ipykernel (>=6.19.2,<7.0.0) ; extra == "dev"
Requires-Dist: isort (>=5.8.0,<6.0.0) ; extra == "test"
Requires-Dist: langchain (>=0.3.19,<0.4.0)
Requires-Dist: markdown (<3.4)
Requires-Dist: mypy (>=1.1.1,<2.0.0) ; extra == "test"
Requires-Dist: pre-commit (>=2.12.0,<3.0.0) ; extra == "dev"
Requires-Dist: protobuf (>=3.20.0,<3.21.0)
Requires-Dist: pytest (>=6.2.4,<7.0.0) ; extra == "test"
Requires-Dist: pytest-cov (>=2.12.0,<3.0.0) ; extra == "test"
Requires-Dist: reflex (>=0.6.3)
Requires-Dist: svgwrite (>=1.4.3,<2.0.0)
Requires-Dist: toml (>=0.10,<0.11) ; extra == "dev"
Requires-Dist: tox (>=3.20.1) ; extra == "dev"
Requires-Dist: twine (>=3.3.0) ; extra == "dev"
Requires-Dist: wandb (>=0.15,<0.16)
